KaifazheTiyanTansuoYuZhongsuFix1/README.md
KaifazheTiyanTansuoYuZhongsuFix1/__init__.py
KaifazheTiyanTansuoYuZhongsuFix1/__main__.py
KaifazheTiyanTansuoYuZhongsuFix1/file.epub
KaifazheTiyanTansuoYuZhongsuFix1/index.html
KaifazheTiyanTansuoYuZhongsuFix1/css/__init__.py
KaifazheTiyanTansuoYuZhongsuFix1/css/annotations.css
KaifazheTiyanTansuoYuZhongsuFix1/css/main.css
KaifazheTiyanTansuoYuZhongsuFix1/css/normalize.css
KaifazheTiyanTansuoYuZhongsuFix1/css/popup.css
KaifazheTiyanTansuoYuZhongsuFix1/font/__init__.py
KaifazheTiyanTansuoYuZhongsuFix1/font/fontello.eot
KaifazheTiyanTansuoYuZhongsuFix1/font/fontello.svg
KaifazheTiyanTansuoYuZhongsuFix1/font/fontello.ttf
KaifazheTiyanTansuoYuZhongsuFix1/font/fontello.woff
KaifazheTiyanTansuoYuZhongsuFix1/img/__init__.py
KaifazheTiyanTansuoYuZhongsuFix1/img/annotator-glyph-sprite.png
KaifazheTiyanTansuoYuZhongsuFix1/img/annotator-icon-sprite.png
KaifazheTiyanTansuoYuZhongsuFix1/img/apple-touch-icon.png
KaifazheTiyanTansuoYuZhongsuFix1/img/cancelfullscreen.png
KaifazheTiyanTansuoYuZhongsuFix1/img/close.png
KaifazheTiyanTansuoYuZhongsuFix1/img/fullscreen.png
KaifazheTiyanTansuoYuZhongsuFix1/img/loader.gif
KaifazheTiyanTansuoYuZhongsuFix1/img/menu-icon.png
KaifazheTiyanTansuoYuZhongsuFix1/img/save.png
KaifazheTiyanTansuoYuZhongsuFix1/img/saved.png
KaifazheTiyanTansuoYuZhongsuFix1/img/settings-s.png
KaifazheTiyanTansuoYuZhongsuFix1/img/settings.png
KaifazheTiyanTansuoYuZhongsuFix1/img/star.png
KaifazheTiyanTansuoYuZhongsuFix1/js/__init__.py
KaifazheTiyanTansuoYuZhongsuFix1/js/epub.js
KaifazheTiyanTansuoYuZhongsuFix1/js/epub.min.js
KaifazheTiyanTansuoYuZhongsuFix1/js/epub.min.map
KaifazheTiyanTansuoYuZhongsuFix1/js/hooks.min.js
KaifazheTiyanTansuoYuZhongsuFix1/js/hooks.min.map
KaifazheTiyanTansuoYuZhongsuFix1/js/reader.js
KaifazheTiyanTansuoYuZhongsuFix1/js/reader.js.map
KaifazheTiyanTansuoYuZhongsuFix1/js/reader.min.js
KaifazheTiyanTansuoYuZhongsuFix1/js/reader.min.map
KaifazheTiyanTansuoYuZhongsuFix1/js/hooks/__init__.py
kaifazhe_tiyan_tansuo_yu_zhongsu_fix1-2025.3.25.1.dist-info/METADATA
kaifazhe_tiyan_tansuo_yu_zhongsu_fix1-2025.3.25.1.dist-info/WHEEL
kaifazhe_tiyan_tansuo_yu_zhongsu_fix1-2025.3.25.1.dist-info/entry_points.txt
kaifazhe_tiyan_tansuo_yu_zhongsu_fix1-2025.3.25.1.dist-info/top_level.txt
kaifazhe_tiyan_tansuo_yu_zhongsu_fix1-2025.3.25.1.dist-info/RECORD
